indeterminatebeam/__init__.py
indeterminatebeam/data_validation.py
indeterminatebeam/indeterminatebeam.py
indeterminatebeam/loading.py
indeterminatebeam/plotly_drawing_aid.py
indeterminatebeam/units.py
indeterminatebeam/version.py
indeterminatebeam-2.4.0.dist-info/licenses/LICENSE.txt
indeterminatebeam-2.4.0.dist-info/METADATA
indeterminatebeam-2.4.0.dist-info/WHEEL
indeterminatebeam-2.4.0.dist-info/top_level.txt
indeterminatebeam-2.4.0.dist-info/RECORD
