Metadata-Version: 2.4
Name: indeterminatebeam
Version: 2.4.0
Summary: A solver for 1D indeterminate beams
Home-page: https://github.com/JesseBonanno/IndeterminateBeam
Download-URL: https://github.com/JesseBonanno/IndeterminateBeam/archive/v2.4.0.tar.gz
Author: Jesse Bonanno
Author-email: jessebonanno@gmail.com
License: MIT
Keywords: statics,indeterminate,beam,civil,structural,shear-force,bending-moment,deflection
Classifier: Development Status :: 3 - Alpha
Classifier: License :: OSI Approved :: MIT License
Classifier: Programming Language :: Python :: 3
Classifier: Programming Language :: Python :: 3.4
Classifier: Programming Language :: Python :: 3.5
Classifier: Programming Language :: Python :: 3.6
License-File: LICENSE.txt
Requires-Dist: matplotlib
Requires-Dist: numpy
Requires-Dist: sympy>=1.10
Requires-Dist: plotly>=4.14.1
Dynamic: author
Dynamic: author-email
Dynamic: classifier
Dynamic: description
Dynamic: description-content-type
Dynamic: download-url
Dynamic: home-page
Dynamic: keywords
Dynamic: license
Dynamic: license-file
Dynamic: requires-dist
Dynamic: summary
